ez_setup.py
qdupe.py
setup.py
bin/qdupe
qdupe.egg-info/PKG-INFO
qdupe.egg-info/SOURCES.txt
qdupe.egg-info/dependency_links.txt
qdupe.egg-info/top_level.txt