Metadata-Version: 1.0
Name: qdupe
Version: 0.1
Summary: A command-line utility to quickly find duplicate files
Home-page: http://github.com/cwilper/qdupe
Author: Chris Wilper
Author-email: cwilper@gmail.com
License: UNKNOWN
Platform: UNKNOWN
Classifier: Development Status :: 4 - Beta
Classifier: Environment :: Console
Classifier: License :: OSI Approved :: Apache Software License
Classifier: Operating System :: OS Independent
Classifier: Programming Language :: Python :: 2
Classifier: Topic :: System :: Archiving
Classifier: Topic :: System :: Filesystems
Classifier: Topic :: System :: Systems Administration
Classifier: Topic :: Utilities
